dran2/__init__.py
dran2/_auto.py
dran2/_cli.py
dran2/_docs.py
dran2/_gui.py
dran2/config.py
dran2/cli/__init__.py
dran2/common/__init__.py
dran2/common/calibrate.py
dran2/common/contextManagers.py
dran2/common/dataProcessingFlowManager.py
dran2/common/dialog_app.py
dran2/common/driftScanAttributes.py
dran2/common/driftScanData.py
dran2/common/driftScans.py
dran2/common/enums.py
dran2/common/exceptions.py
dran2/common/file_handler.py
dran2/common/fitting.py
dran2/common/getResources.py
dran2/common/logConfiguration.py
dran2/common/miscellaneousFunctions.py
dran2/common/msgConfiguration.py
dran2/common/observation.py
dran2/common/plotting.py
dran2/common/sqlite_db.py
dran2/common/variables.py
dran2/docs/readme_first.txt
dran2/docs/runMeToBuildDocs.py
dran2/docs/dran-build/_sources/index.rst.txt
dran2/docs/dran-build/_sources/docs/modules.rst.txt
dran2/docs/dran-build/_sources/docs/src.cli.rst.txt
dran2/docs/dran-build/_sources/docs/src.common.rst.txt
dran2/docs/dran-build/_sources/docs/src.gui.rst.txt
dran2/docs/dran-build/_sources/docs/src.predefs.rst.txt
dran2/docs/dran-build/_sources/docs/src.rst.txt
dran2/docs/dran-build/_sources/extras/calibration.rst.txt
dran2/docs/dran-build/_sources/extras/caveats.rst.txt
dran2/docs/dran-build/_sources/extras/changelog.rst.txt
dran2/docs/dran-build/_sources/extras/cli.rst.txt
dran2/docs/dran-build/_sources/extras/commands.rst.txt
dran2/docs/dran-build/_sources/extras/common_issues.rst.txt
dran2/docs/dran-build/_sources/extras/gui.rst.txt
dran2/docs/dran-build/_sources/extras/installation.rst.txt
dran2/docs/dran-build/_sources/extras/jupiter_calibration.rst.txt
dran2/docs/dran-build/_sources/extras/quickstart.rst.txt
dran2/docs/dran-build/_sources/extras/radio_sources.rst.txt
dran2/docs/dran-build/_sources/extras/rfi.rst.txt
dran2/docs/dran-build/_sources/extras/calibration/cx-band.rst.txt
dran2/docs/dran-build/_sources/extras/calibration/k-band.rst.txt
dran2/docs/dran-build/_sources/extras/calibration/ku-band.rst.txt
dran2-1.4.7.dist-info/AUTHORS.rst
dran2-1.4.7.dist-info/LICENSE.txt
dran2-1.4.7.dist-info/METADATA
dran2-1.4.7.dist-info/WHEEL
dran2-1.4.7.dist-info/entry_points.txt
dran2-1.4.7.dist-info/top_level.txt
dran2-1.4.7.dist-info/RECORD
