Metadata-Version: 2.1
Name: dran2
Version: 1.4.7
Summary: Data reduction and analysis of HartRAO 26m telescope drift scans
Author-email: Pfesesani van Zyl <pfesi24@gmail.com>
Maintainer-email: Pfesesani van Zyl <pfesi24@gmail.com>
License: MIT License
Project-URL: Documentation, https://dran2.readthedocs.io/en/latest/
Project-URL: Changelog, https://dran2.readthedocs.io/en/latest/extras/changelog.html
Project-URL: Issues, https://github.com/Pfesi/dran2/issues
Project-URL: Repository, https://github.com/Pfesi/dran2
Keywords: dran,single-dish,hartrao,sarao
Classifier: Development Status :: 4 - Beta
Classifier: Intended Audience :: End Users/Desktop
Classifier: License :: OSI Approved :: MIT License
Classifier: Programming Language :: Python :: 3.11
Classifier: Topic :: Scientific/Engineering :: Astronomy
Classifier: Operating System :: OS Independent
Requires-Python: >=3.10
License-File: LICENSE.txt
License-File: AUTHORS.rst
Requires-Dist: astropy==6.1.3
Requires-Dist: astropy-iers-data==0.2024.9.2.0.33.23
Requires-Dist: build==1.2.1
Requires-Dist: certifi==2024.8.30
Requires-Dist: charset-normalizer==3.3.2
Requires-Dist: contourpy==1.3.0
Requires-Dist: cycler==0.12.1
Requires-Dist: docutils==0.21.2
Requires-Dist: fonttools==4.53.1
Requires-Dist: idna==3.8
Requires-Dist: importlib_metadata==8.4.0
Requires-Dist: jaraco.classes==3.4.0
Requires-Dist: jaraco.context==6.0.1
Requires-Dist: jaraco.functools==4.0.2
Requires-Dist: joblib==1.4.2
Requires-Dist: keyring==25.3.0
Requires-Dist: kiwisolver==1.4.5
Requires-Dist: markdown-it-py==3.0.0
Requires-Dist: matplotlib==3.9.2
Requires-Dist: mdurl==0.1.2
Requires-Dist: more-itertools==10.4.0
Requires-Dist: nh3==0.2.18
Requires-Dist: numpy==2.1.0
Requires-Dist: packaging==24.1
Requires-Dist: pandas==2.2.2
Requires-Dist: pillow==10.4.0
Requires-Dist: pkginfo==1.10.0
Requires-Dist: psutil==6.0.0
Requires-Dist: pyerfa==2.0.1.4
Requires-Dist: Pygments==2.18.0
Requires-Dist: pyparsing==3.1.4
Requires-Dist: pyproject_hooks==1.1.0
Requires-Dist: PyQt5==5.15.11
Requires-Dist: PyQt5-Qt5==5.15.14
Requires-Dist: PyQt5_sip==12.15.0
Requires-Dist: python-dateutil==2.9.0.post0
Requires-Dist: pytz==2024.1
Requires-Dist: PyYAML==6.0.2
Requires-Dist: readme_renderer==44.0
Requires-Dist: requests==2.32.3
Requires-Dist: requests-toolbelt==1.0.0
Requires-Dist: rfc3986==2.0.0
Requires-Dist: rich==13.8.0
Requires-Dist: scikit-learn==1.5.1
Requires-Dist: scipy==1.14.1
Requires-Dist: setuptools==72.1.0
Requires-Dist: six==1.16.0
Requires-Dist: threadpoolctl==3.5.0
Requires-Dist: twine==5.1.1
Requires-Dist: tzdata==2024.1
Requires-Dist: urllib3==2.2.2
Requires-Dist: wheel==0.43.0
Requires-Dist: zipp==3.20.1
